scriptmark/__init__.py
scriptmark/main.py
scriptmark/run_test.py
scriptmark/summary.py
scriptmark/utils.py
scriptmark-0.1.1.dist-info/WHEEL
scriptmark-0.1.1.dist-info/entry_points.txt
scriptmark-0.1.1.dist-info/METADATA
scriptmark-0.1.1.dist-info/RECORD
