Metadata-Version: 2.3
Name: scriptmark
Version: 0.1.1
Summary: 一个可扩展的、用于自动评分学生编程作业的CLI工具。目前仅实现了基于pytest的
Keywords: grader,pytest,education,autograding
Author: Acture
Author-email: Acture <acturea@gmail.com>
License: GPL-3.0-or-later
Classifier: Development Status :: 3 - Alpha
Classifier: Intended Audience :: Developers
Classifier: Intended Audience :: Education
Classifier: Operating System :: OS Independent
Classifier: Programming Language :: Python :: 3
Classifier: Programming Language :: Python :: 3.14
Requires-Dist: pydantic>=2.12.3
Requires-Dist: pytest>=8.4.2
Requires-Dist: pytest-timeout>=2.4.0
Requires-Dist: rich>=14.2.0
Requires-Dist: typer>=0.20.0
Requires-Python: >=3.10
